{ "height":32,
 "layers":[
        {
         "draworder":"topdown",
         "height":100,
         "name":"Object Layer 1",
         "objects":[
                {
                 "height":52.2466039707419,
                 "id":3,
                 "name":"",
                 "rotation":0,
                 "type":"",
                 "visible":true,
                 "width":3648,
                 "x":64,
                 "y":832
                }, 
                {
                 "height":32,
                 "id":33,
                 "name":"",
                 "rotation":0,
                 "type":"",
                 "visible":true,
                 "width":1472,
                 "x":6464,
                 "y":640
                }, 
                {
                 "gid":2,
                 "height":134,
                 "id":47,
                 "name":"",
                 "rotation":0,
                 "type":"",
                 "visible":true,
                 "width":128,
                 "x":4925.33333333333,
                 "y":428.242424242424
                }, 
                {
                 "height":32,
                 "id":70,
                 "name":"",
                 "rotation":0,
                 "type":"",
                 "visible":true,
                 "width":1856,
                 "x":4416,
                 "y":672
                }, 
                {
                 "gid":1,
                 "height":58,
                 "id":140,
                 "name":"",
                 "rotation":0,
                 "type":"",
                 "visible":true,
                 "width":71,
                 "x":992,
                 "y":576
                }, 
                {
                 "gid":1,
                 "height":58,
                 "id":142,
                 "name":"",
                 "rotation":0,
                 "type":"",
                 "visible":true,
                 "width":71,
                 "x":992,
                 "y":672
                }, 
                {
                 "gid":1,
                 "height":58,
                 "id":144,
                 "name":"",
                 "rotation":0,
                 "type":"",
                 "visible":true,
                 "width":71,
                 "x":1056,
                 "y":704
                }, 
                {
                 "gid":1,
                 "height":68,
                 "id":145,
                 "name":"",
                 "rotation":0,
                 "type":"",
                 "visible":true,
                 "width":77,
                 "x":1056,
                 "y":544
                }, 
                {
                 "gid":1,
                 "height":58,
                 "id":146,
                 "name":"",
                 "rotation":0,
                 "type":"",
                 "visible":true,
                 "width":71,
                 "x":1184,
                 "y":544
                }, 
                {
                 "gid":1,
                 "height":58,
                 "id":148,
                 "name":"",
                 "rotation":0,
                 "type":"",
                 "visible":true,
                 "width":71,
                 "x":1184,
                 "y":608
                }, 
                {
                 "gid":1,
                 "height":58,
                 "id":150,
                 "name":"",
                 "rotation":0,
                 "type":"",
                 "visible":true,
                 "width":71,
                 "x":1184,
                 "y":704
                }, 
                {
                 "gid":1,
                 "height":58,
                 "id":153,
                 "name":"",
                 "rotation":0,
                 "type":"",
                 "visible":true,
                 "width":71,
                 "x":1312,
                 "y":608
                }, 
                {
                 "gid":1,
                 "height":58,
                 "id":154,
                 "name":"",
                 "rotation":0,
                 "type":"",
                 "visible":true,
                 "width":71,
                 "x":1312,
                 "y":544
                }, 
                {
                 "gid":1,
                 "height":58,
                 "id":155,
                 "name":"",
                 "rotation":0,
                 "type":"",
                 "visible":true,
                 "width":71,
                 "x":1312,
                 "y":704
                }, 
                {
                 "gid":1,
                 "height":58,
                 "id":157,
                 "name":"",
                 "rotation":0,
                 "type":"",
                 "visible":true,
                 "width":71,
                 "x":1248,
                 "y":640
                }, 
                {
                 "gid":1,
                 "height":58,
                 "id":158,
                 "name":"",
                 "rotation":0,
                 "type":"",
                 "visible":true,
                 "width":71,
                 "x":1440,
                 "y":544
                }, 
                {
                 "gid":1,
                 "height":58,
                 "id":159,
                 "name":"",
                 "rotation":0,
                 "type":"",
                 "visible":true,
                 "width":71,
                 "x":1440,
                 "y":704
                }, 
                {
                 "gid":1,
                 "height":58,
                 "id":160,
                 "name":"",
                 "rotation":0,
                 "type":"",
                 "visible":true,
                 "width":71,
                 "x":1440,
                 "y":640
                }, 
                {
                 "gid":1,
                 "height":58,
                 "id":164,
                 "name":"",
                 "rotation":0,
                 "type":"",
                 "visible":true,
                 "width":71,
                 "x":1568,
                 "y":704
                }, 
                {
                 "gid":1,
                 "height":58,
                 "id":165,
                 "name":"",
                 "rotation":0,
                 "type":"",
                 "visible":true,
                 "width":71,
                 "x":1568,
                 "y":544
                }, 
                {
                 "gid":1,
                 "height":58,
                 "id":167,
                 "name":"",
                 "rotation":0,
                 "type":"",
                 "visible":true,
                 "width":71,
                 "x":1568,
                 "y":640
                }, 
                {
                 "gid":1,
                 "height":58,
                 "id":169,
                 "name":"",
                 "rotation":0,
                 "type":"",
                 "visible":true,
                 "width":71,
                 "x":1760,
                 "y":704
                }, 
                {
                 "gid":1,
                 "height":58,
                 "id":170,
                 "name":"",
                 "rotation":0,
                 "type":"",
                 "visible":true,
                 "width":71,
                 "x":1760,
                 "y":544
                }, 
                {
                 "gid":1,
                 "height":58,
                 "id":172,
                 "name":"",
                 "rotation":0,
                 "type":"",
                 "visible":true,
                 "width":71,
                 "x":1760,
                 "y":640
                }, 
                {
                 "gid":1,
                 "height":58,
                 "id":173,
                 "name":"",
                 "rotation":0,
                 "type":"",
                 "visible":true,
                 "width":71,
                 "x":1664,
                 "y":640
                }, 
                {
                 "gid":1,
                 "height":58,
                 "id":175,
                 "name":"",
                 "rotation":0,
                 "type":"",
                 "visible":true,
                 "width":71,
                 "x":1696,
                 "y":576
                }, 
                {
                 "gid":1,
                 "height":58,
                 "id":176,
                 "name":"",
                 "rotation":0,
                 "type":"",
                 "visible":true,
                 "width":71,
                 "x":1632,
                 "y":576
                }, 
                {
                 "gid":1,
                 "height":58,
                 "id":178,
                 "name":"",
                 "rotation":0,
                 "type":"",
                 "visible":true,
                 "width":71,
                 "x":1888,
                 "y":576
                }, 
                {
                 "gid":1,
                 "height":58,
                 "id":179,
                 "name":"",
                 "rotation":0,
                 "type":"",
                 "visible":true,
                 "width":71,
                 "x":1888,
                 "y":704
                }, 
                {
                 "gid":1,
                 "height":58,
                 "id":182,
                 "name":"",
                 "rotation":0,
                 "type":"",
                 "visible":true,
                 "width":71,
                 "x":1888,
                 "y":638.636363636364
                }, 
                {
                 "gid":1,
                 "height":58,
                 "id":183,
                 "name":"",
                 "rotation":0,
                 "type":"",
                 "visible":true,
                 "width":71,
                 "x":2016,
                 "y":576
                }, 
                {
                 "gid":1,
                 "height":58,
                 "id":184,
                 "name":"",
                 "rotation":0,
                 "type":"",
                 "visible":true,
                 "width":71,
                 "x":2016,
                 "y":704
                }, 
                {
                 "gid":1,
                 "height":58,
                 "id":187,
                 "name":"",
                 "rotation":0,
                 "type":"",
                 "visible":true,
                 "width":71,
                 "x":2016,
                 "y":640
                }, 
                {
                 "gid":1,
                 "height":58,
                 "id":189,
                 "name":"",
                 "rotation":0,
                 "type":"",
                 "visible":true,
                 "width":71,
                 "x":2144,
                 "y":704
                }, 
                {
                 "gid":1,
                 "height":58,
                 "id":190,
                 "name":"",
                 "rotation":0,
                 "type":"",
                 "visible":true,
                 "width":71,
                 "x":2144,
                 "y":576
                }, 
                {
                 "gid":1,
                 "height":58,
                 "id":192,
                 "name":"",
                 "rotation":0,
                 "type":"",
                 "visible":true,
                 "width":71,
                 "x":2144,
                 "y":640
                }, 
                {
                 "gid":1,
                 "height":58,
                 "id":193,
                 "name":"",
                 "rotation":0,
                 "type":"",
                 "visible":true,
                 "width":71,
                 "x":2304,
                 "y":640
                }, 
                {
                 "gid":1,
                 "height":58,
                 "id":195,
                 "name":"",
                 "rotation":0,
                 "type":"",
                 "visible":true,
                 "width":71,
                 "x":2304,
                 "y":576
                }, 
                {
                 "gid":1,
                 "height":58,
                 "id":196,
                 "name":"",
                 "rotation":0,
                 "type":"",
                 "visible":true,
                 "width":71,
                 "x":2304,
                 "y":704
                }, 
                {
                 "gid":1,
                 "height":58,
                 "id":198,
                 "name":"",
                 "rotation":0,
                 "type":"",
                 "visible":true,
                 "width":71,
                 "x":2528,
                 "y":544
                }, 
                {
                 "gid":1,
                 "height":58,
                 "id":199,
                 "name":"",
                 "rotation":0,
                 "type":"",
                 "visible":true,
                 "width":71,
                 "x":2464,
                 "y":544
                }, 
                {
                 "gid":1,
                 "height":58,
                 "id":202,
                 "name":"",
                 "rotation":0,
                 "type":"",
                 "visible":true,
                 "width":71,
                 "x":2432,
                 "y":608
                }, 
                {
                 "gid":1,
                 "height":58,
                 "id":203,
                 "name":"",
                 "rotation":0,
                 "type":"",
                 "visible":true,
                 "width":71,
                 "x":2432,
                 "y":672
                }, 
                {
                 "gid":1,
                 "height":58,
                 "id":204,
                 "name":"",
                 "rotation":0,
                 "type":"",
                 "visible":true,
                 "width":71,
                 "x":2496,
                 "y":704
                }, 
                {
                 "gid":1,
                 "height":58,
                 "id":205,
                 "name":"",
                 "rotation":0,
                 "type":"",
                 "visible":true,
                 "width":71,
                 "x":2560,
                 "y":704
                }, 
                {
                 "gid":1,
                 "height":58,
                 "id":206,
                 "name":"",
                 "rotation":0,
                 "type":"",
                 "visible":true,
                 "width":71,
                 "x":2560,
                 "y":640
                }, 
                {
                 "gid":1,
                 "height":58,
                 "id":209,
                 "name":"",
                 "rotation":0,
                 "type":"",
                 "visible":true,
                 "width":71,
                 "x":1952,
                 "y":544
                }, 
                {
                 "gid":1,
                 "height":58,
                 "id":212,
                 "name":"",
                 "rotation":0,
                 "type":"",
                 "visible":true,
                 "width":71,
                 "x":1952,
                 "y":640
                }, 
                {
                 "gid":1,
                 "height":58,
                 "id":214,
                 "name":"",
                 "rotation":0,
                 "type":"",
                 "visible":true,
                 "width":71,
                 "x":2208,
                 "y":608
                }, 
                {
                 "gid":1,
                 "height":58,
                 "id":216,
                 "name":"",
                 "rotation":0,
                 "type":"",
                 "visible":true,
                 "width":71,
                 "x":2240,
                 "y":672
                }, 
                {
                 "gid":1,
                 "height":58,
                 "id":218,
                 "name":"",
                 "rotation":0,
                 "type":"",
                 "visible":true,
                 "width":71,
                 "x":2688,
                 "y":666
                }, 
                {
                 "gid":1,
                 "height":58,
                 "id":220,
                 "name":"",
                 "rotation":0,
                 "type":"",
                 "visible":true,
                 "width":71,
                 "x":2816,
                 "y":672
                }, 
                {
                 "gid":1,
                 "height":58,
                 "id":222,
                 "name":"",
                 "rotation":0,
                 "type":"",
                 "visible":true,
                 "width":71,
                 "x":2816,
                 "y":608
                }, 
                {
                 "gid":1,
                 "height":58,
                 "id":223,
                 "name":"",
                 "rotation":0,
                 "type":"",
                 "visible":true,
                 "width":71,
                 "x":2690,
                 "y":608
                }, 
                {
                 "gid":1,
                 "height":58,
                 "id":226,
                 "name":"",
                 "rotation":0,
                 "type":"",
                 "visible":true,
                 "width":71,
                 "x":2752,
                 "y":576
                }, 
                {
                 "gid":1,
                 "height":58,
                 "id":230,
                 "name":"",
                 "rotation":0,
                 "type":"",
                 "visible":true,
                 "width":71,
                 "x":2752,
                 "y":704
                }, 
                {
                 "gid":1,
                 "height":58,
                 "id":239,
                 "name":"",
                 "rotation":0,
                 "type":"",
                 "visible":true,
                 "width":71,
                 "x":4181.16601515152,
                 "y":670.636106060606
                }, 
                {
                 "gid":1,
                 "height":58,
                 "id":240,
                 "name":"",
                 "rotation":0,
                 "type":"",
                 "visible":true,
                 "width":71,
                 "x":4100.31801515152,
                 "y":716.818106060606
                }, 
                {
                 "gid":1,
                 "height":58,
                 "id":241,
                 "name":"",
                 "rotation":0,
                 "type":"",
                 "visible":true,
                 "width":71,
                 "x":4087.22701515151,
                 "y":437.303106060606
                }, 
                {
                 "gid":1,
                 "height":58,
                 "id":242,
                 "name":"",
                 "rotation":0,
                 "type":"",
                 "visible":true,
                 "width":71,
                 "x":4244.80301515151,
                 "y":631.242106060606
                }, 
                {
                 "gid":1,
                 "height":58,
                 "id":243,
                 "name":"",
                 "rotation":0,
                 "type":"",
                 "visible":true,
                 "width":71,
                 "x":4159.95401515151,
                 "y":479.727106060606
                }, 
                {
                 "gid":1,
                 "height":58,
                 "id":244,
                 "name":"",
                 "rotation":0,
                 "type":"",
                 "visible":true,
                 "width":71,
                 "x":4272.07601515152,
                 "y":564.576106060606
                }, 
                {
                 "gid":1,
                 "height":58,
                 "id":245,
                 "name":"",
                 "rotation":0,
                 "type":"",
                 "visible":true,
                 "width":71,
                 "x":4221.53001515151,
                 "y":515.121106060606
                }, 
                {
                 "gid":2,
                 "height":101,
                 "id":246,
                 "name":"",
                 "rotation":0,
                 "type":"",
                 "visible":true,
                 "width":120,
                 "x":5196,
                 "y":434
                }, 
                {
                 "gid":2,
                 "height":101,
                 "id":247,
                 "name":"",
                 "rotation":0,
                 "type":"",
                 "visible":true,
                 "width":120,
                 "x":5412,
                 "y":490
                }, 
                {
                 "gid":2,
                 "height":101,
                 "id":248,
                 "name":"",
                 "rotation":0,
                 "type":"",
                 "visible":true,
                 "width":120,
                 "x":5582.42424242424,
                 "y":540.909090909091
                }, 
                {
                 "gid":2,
                 "height":101,
                 "id":249,
                 "name":"",
                 "rotation":0,
                 "type":"",
                 "visible":true,
                 "width":120,
                 "x":5764.24242424242,
                 "y":546.969696969697
                }, 
                {
                 "gid":2,
                 "height":101,
                 "id":250,
                 "name":"",
                 "rotation":0,
                 "type":"",
                 "visible":true,
                 "width":120,
                 "x":5921.81818181818,
                 "y":556.060606060606
                }, 
                {
                 "gid":2,
                 "height":101,
                 "id":251,
                 "name":"",
                 "rotation":0,
                 "type":"",
                 "visible":true,
                 "width":120,
                 "x":6064.24242424242,
                 "y":510.606060606061
                }, 
                {
                 "gid":2,
                 "height":101,
                 "id":252,
                 "name":"",
                 "rotation":0,
                 "type":"",
                 "visible":true,
                 "width":120,
                 "x":6197.57575757576,
                 "y":456.060606060606
                }, 
                {
                 "gid":2,
                 "height":101,
                 "id":253,
                 "name":"",
                 "rotation":0,
                 "type":"",
                 "visible":true,
                 "width":120,
                 "x":3567.27272727273,
                 "y":613.636363636364
                }, 
                {
                 "gid":2,
                 "height":101,
                 "id":255,
                 "name":"",
                 "rotation":0,
                 "type":"",
                 "visible":true,
                 "width":120,
                 "x":3718.78787878788,
                 "y":713.636363636364
                }, 
                {
                 "gid":2,
                 "height":101,
                 "id":256,
                 "name":"",
                 "rotation":0,
                 "type":"",
                 "visible":true,
                 "width":120,
                 "x":3873.33333333333,
                 "y":807.575757575758
                }, 
                {
                 "gid":2,
                 "height":101,
                 "id":257,
                 "name":"",
                 "rotation":0,
                 "type":"",
                 "visible":true,
                 "width":120,
                 "x":997.575757575758,
                 "y":280.30303030303
                }, 
                {
                 "gid":2,
                 "height":101,
                 "id":258,
                 "name":"",
                 "rotation":0,
                 "type":"",
                 "visible":true,
                 "width":120,
                 "x":1133.93939393939,
                 "y":228.787878787879
                }, 
                {
                 "gid":2,
                 "height":101,
                 "id":259,
                 "name":"",
                 "rotation":0,
                 "type":"",
                 "visible":true,
                 "width":120,
                 "x":1315.75757575758,
                 "y":222.727272727273
                }, 
                {
                 "gid":2,
                 "height":101,
                 "id":260,
                 "name":"",
                 "rotation":0,
                 "type":"",
                 "visible":true,
                 "width":120,
                 "x":1533.93939393939,
                 "y":256.060606060606
                }, 
                {
                 "gid":2,
                 "height":101,
                 "id":261,
                 "name":"",
                 "rotation":0,
                 "type":"",
                 "visible":true,
                 "width":120,
                 "x":1785.45454545455,
                 "y":274.242424242424
                }, 
                {
                 "gid":2,
                 "height":101,
                 "id":262,
                 "name":"",
                 "rotation":0,
                 "type":"",
                 "visible":true,
                 "width":120,
                 "x":2368,
                 "y":958
                }, 
                {
                 "gid":2,
                 "height":101,
                 "id":263,
                 "name":"",
                 "rotation":0,
                 "type":"",
                 "visible":true,
                 "width":120,
                 "x":2536,
                 "y":982
                }, 
                {
                 "gid":2,
                 "height":101,
                 "id":264,
                 "name":"",
                 "rotation":0,
                 "type":"",
                 "visible":true,
                 "width":120,
                 "x":2648,
                 "y":286
                }, 
                {
                 "gid":2,
                 "height":101,
                 "id":265,
                 "name":"",
                 "rotation":0,
                 "type":"",
                 "visible":true,
                 "width":120,
                 "x":2828,
                 "y":290
                }, 
                {
                 "gid":2,
                 "height":101,
                 "id":266,
                 "name":"",
                 "rotation":0,
                 "type":"",
                 "visible":true,
                 "width":120,
                 "x":3008,
                 "y":326
                }, 
                {
                 "gid":2,
                 "height":101,
                 "id":267,
                 "name":"",
                 "rotation":0,
                 "type":"",
                 "visible":true,
                 "width":120,
                 "x":3268,
                 "y":810
                }, 
                {
                 "gid":2,
                 "height":101,
                 "id":268,
                 "name":"",
                 "rotation":0,
                 "type":"",
                 "visible":true,
                 "width":120,
                 "x":3396,
                 "y":710
                }, 
                {
                 "gid":2,
                 "height":101,
                 "id":269,
                 "name":"",
                 "rotation":0,
                 "type":"",
                 "visible":true,
                 "width":120,
                 "x":4296,
                 "y":194
                }, 
                {
                 "gid":2,
                 "height":101,
                 "id":270,
                 "name":"",
                 "rotation":0,
                 "type":"",
                 "visible":true,
                 "width":120,
                 "x":4456,
                 "y":198
                }, 
                {
                 "gid":2,
                 "height":101,
                 "id":271,
                 "name":"",
                 "rotation":0,
                 "type":"",
                 "visible":true,
                 "width":120,
                 "x":536,
                 "y":414
                }],
         "opacity":1,
         "type":"objectgroup",
         "visible":true,
         "width":100,
         "x":0,
         "y":0
        }],
 "nextobjectid":274,
 "orientation":"orthogonal",
 "renderorder":"right-down",
 "tileheight":32,
 "tilesets":[
        {
         "columns":0,
         "firstgid":1,
         "margin":0,
         "name":"Objects",
         "spacing":0,
         "tilecount":2,
         "tileheight":134,
         "tiles":
            {
             "0":
                {
                 "image":"img\/torta.png"
                },
             "1":
                {
                 "image":"img\/Enemy.png"
                }
            },
         "tilewidth":128
        }],
 "tilewidth":32,
 "version":1,
 "width":250
}